mcp_server/__init__.py
mcp_server/cli.py
mcp_server/main.py
mcp_server/http/__init__.py
mcp_server/http/app.py
mcp_server/http/auth.py
mcp_server/http/mcp_server.py
mcp_server/openproject_client/openproject_api_client/__init__.py
mcp_server/openproject_client/openproject_api_client/api_client.py
mcp_server/openproject_client/openproject_api_client/api_response.py
mcp_server/openproject_client/openproject_api_client/configuration.py
mcp_server/openproject_client/openproject_api_client/exceptions.py
mcp_server/openproject_client/openproject_api_client/rest.py
mcp_server/openproject_client/openproject_api_client/api/__init__.py
mcp_server/openproject_client/openproject_api_client/api/actions_capabilities_api.py
mcp_server/openproject_client/openproject_api_client/api/activities_api.py
mcp_server/openproject_client/openproject_api_client/api/attachments_api.py
mcp_server/openproject_client/openproject_api_client/api/budgets_api.py
mcp_server/openproject_client/openproject_api_client/api/categories_api.py
mcp_server/openproject_client/openproject_api_client/api/collections_api.py
mcp_server/openproject_client/openproject_api_client/api/configuration_api.py
mcp_server/openproject_client/openproject_api_client/api/custom_actions_api.py
mcp_server/openproject_client/openproject_api_client/api/custom_options_api.py
mcp_server/openproject_client/openproject_api_client/api/default_api.py
mcp_server/openproject_client/openproject_api_client/api/documents_api.py
mcp_server/openproject_client/openproject_api_client/api/emoji_reactions_api.py
mcp_server/openproject_client/openproject_api_client/api/favorites_api.py
mcp_server/openproject_client/openproject_api_client/api/file_links0_api.py
mcp_server/openproject_client/openproject_api_client/api/file_links_api.py
mcp_server/openproject_client/openproject_api_client/api/forms_api.py
mcp_server/openproject_client/openproject_api_client/api/grids_api.py
mcp_server/openproject_client/openproject_api_client/api/groups_api.py
mcp_openproject-0.0.2.dist-info/METADATA
mcp_openproject-0.0.2.dist-info/WHEEL
mcp_openproject-0.0.2.dist-info/entry_points.txt
mcp_openproject-0.0.2.dist-info/top_level.txt
mcp_openproject-0.0.2.dist-info/RECORD
