Metadata-Version: 2.4
Name: mcp-openproject
Version: 0.0.2
Summary: OpenProject MCP Server for AI Integration - Production Ready v0.0.1
Author-email: MCP OpenProject Team <contact@mcp-openproject.dev>
License: MIT
Project-URL: Homepage, https://github.com/your-org/mcp-openproject
Project-URL: Repository, https://github.com/your-org/mcp-openproject.git
Project-URL: Issues, https://github.com/your-org/mcp-openproject/issues
Keywords: mcp,openproject,ai,integration,windsurf,claude
Classifier: Development Status :: 4 - Beta
Classifier: Intended Audience :: Developers
Classifier: Intended Audience :: End Users/Desktop
Classifier: License :: OSI Approved :: MIT License
Classifier: Operating System :: OS Independent
Classifier: Programming Language :: Python :: 3
Classifier: Programming Language :: Python :: 3.10
Classifier: Programming Language :: Python :: 3.11
Classifier: Programming Language :: Python :: 3.12
Classifier: Programming Language :: Python :: 3.13
Classifier: Topic :: Software Development :: Libraries :: Python Modules
Classifier: Topic :: Office/Business :: Scheduling
Requires-Python: >=3.10
Requires-Dist: fastmcp>=0.3.0
Requires-Dist: httpx>=0.25.0
Requires-Dist: pydantic>=2.0.0
Requires-Dist: backoff>=2.2.1
Requires-Dist: python-dateutil>=2.8.0
Requires-Dist: urllib3>=1.26.0
Requires-Dist: fastapi>=0.104.0
Requires-Dist: uvicorn[standard]>=0.24.0
Requires-Dist: fastapi-mcp>=0.4.0
Requires-Dist: structlog>=23.0.0
Provides-Extra: dev
Requires-Dist: pytest>=7.4.0; extra == "dev"
Requires-Dist: pytest-asyncio>=0.21.0; extra == "dev"
Requires-Dist: pytest-cov>=4.1.0; extra == "dev"
Requires-Dist: black>=23.0.0; extra == "dev"
Requires-Dist: ruff>=0.1.0; extra == "dev"
Requires-Dist: mypy>=1.0.0; extra == "dev"
Requires-Dist: pre-commit>=3.0.0; extra == "dev"
Provides-Extra: full
Requires-Dist: mcp-openproject[dev]; extra == "full"
Requires-Dist: uvicorn[standard]>=0.24.0; extra == "full"
Requires-Dist: structlog>=23.0.0; extra == "full"
Requires-Dist: python-dotenv>=1.0.1; extra == "full"
Requires-Dist: cryptography>=41.0.0; extra == "full"
Provides-Extra: http-transport
Requires-Dist: fastapi>=0.104.0; extra == "http-transport"
Requires-Dist: uvicorn[standard]>=0.24.0; extra == "http-transport"
Requires-Dist: fastapi_mcp>=0.4.0; extra == "http-transport"
Requires-Dist: structlog>=23.0.0; extra == "http-transport"
Provides-Extra: openproject-client
Requires-Dist: openapi-generator-cli>=7.0.0; extra == "openproject-client"
Provides-Extra: ai-backend
Requires-Dist: fastapi>=0.104.0; extra == "ai-backend"
Requires-Dist: uvicorn[standard]>=0.24.0; extra == "ai-backend"
Requires-Dist: langchain>=0.1.0; extra == "ai-backend"
Requires-Dist: langchain-openai>=0.0.2; extra == "ai-backend"
Requires-Dist: langchain-mcp-adapters>=0.1.11; extra == "ai-backend"
Requires-Dist: redis>=5.0.0; extra == "ai-backend"
Requires-Dist: sqlalchemy>=2.0.0; extra == "ai-backend"
Requires-Dist: jinja2>=3.1.0; extra == "ai-backend"
Requires-Dist: python-multipart>=0.0.6; extra == "ai-backend"
Requires-Dist: aiofiles>=23.0.0; extra == "ai-backend"
Requires-Dist: watchfiles>=0.20.0; extra == "ai-backend"
Requires-Dist: PyJWT>=2.8.0; extra == "ai-backend"
Requires-Dist: prometheus-client>=0.19.0; extra == "ai-backend"
Provides-Extra: database
Requires-Dist: asyncpg<0.31.0,>=0.30.0; extra == "database"
Provides-Extra: all
Requires-Dist: mcp-openproject[ai-backend,database,full,openproject-client]; extra == "all"
